egcd/__init__.py
egcd/egcd.py
egcd-3.0.0.dist-info/licenses/LICENSE
egcd-3.0.0.dist-info/METADATA
egcd-3.0.0.dist-info/WHEEL
egcd-3.0.0.dist-info/top_level.txt
egcd-3.0.0.dist-info/RECORD
